netlogopy/__init__.py
netlogopy/netlogopy.nlogo
netlogopy/netlogopy.py
netlogopy-0.0.19.data/data/netlogo/netlogopy.nlogo
netlogopy2/__init__.py
netlogopy2/netlogopy.py
netlogopy-0.0.19.dist-info/LICENSE
netlogopy-0.0.19.dist-info/METADATA
netlogopy-0.0.19.dist-info/WHEEL
netlogopy-0.0.19.dist-info/top_level.txt
netlogopy-0.0.19.dist-info/RECORD
