Metadata-Version: 2.2
Name: netlogopy
Version: 0.0.19
Summary: netlogopy : Usage netlogo by python
Author: BOUAZIZ (BOUAZIZ NOURDDINE)
Author-email: <nourddine.bouaziz.dz@gmail.com>
Keywords: python,netlogo,simulation,multi agent
Classifier: Development Status :: 1 - Planning
Classifier: Intended Audience :: Developers
Classifier: Programming Language :: Python :: 3
Classifier: Operating System :: Unix
Classifier: Operating System :: MacOS :: MacOS X
Classifier: Operating System :: Microsoft :: Windows
License-File: LICENSE
Requires-Dist: nl4py
Dynamic: author
Dynamic: author-email
Dynamic: classifier
Dynamic: description
Dynamic: description-content-type
Dynamic: keywords
Dynamic: requires-dist
Dynamic: summary
